setup.cfg
setup.py
format_datetime/__init__.py
format_datetime.egg-info/PKG-INFO
format_datetime.egg-info/SOURCES.txt
format_datetime.egg-info/dependency_links.txt
format_datetime.egg-info/entry_points.txt
format_datetime.egg-info/top_level.txt
format_datetime.egg-info/zip-safe