Metadata-Version: 1.0
Name: format-datetime
Version: 0.6dev
Summary: Helpers to properly print date and time (strftime replacement).
Home-page: https://bitbucket.org/niels_mfo/format_datetime
Author: Niels Ranosch
Author-email: ranosch@mfo.de
License: MIT
Keywords: date time international strftime locale format datetime
Platform: UNKNOWN
